Metadata-Version: 1.0
Name: headers-converter
Version: 0.0
Summary: Convert Headers From Browser Str To Dict
Home-page: UNKNOWN
Author: UNKNOWN
Author-email: herew26@gmail.com
License: UNKNOWN
Platform: UNKNOWN
